servicectl/__init__.py
servicectl/container_controller.py
servicectl/docker_controller.py
servicectl/exceptions.py
servicectl/service_controller.py
servicectl-0.0.0.dist-info/LICENSE
servicectl-0.0.0.dist-info/WHEEL
servicectl-0.0.0.dist-info/METADATA
servicectl-0.0.0.dist-info/RECORD
