Metadata-Version: 2.1
Name: servicectl
Version: 0.0.0
Summary: Docker stack deployment manager
Home-page: https://github.com/TheEdgeOfRage/servicectl
License: BSD-3-Clause
Keywords: docker,service,deployment
Author: Pavle Portic
Author-email: pavle.portic@tilda.center
Requires-Python: >=3.6,<4.0
Classifier: License :: OSI Approved :: BSD License
Classifier: Programming Language :: Python :: 3
Classifier: Programming Language :: Python :: 3.6
Classifier: Programming Language :: Python :: 3.7
Classifier: Programming Language :: Python :: 3.8
Requires-Dist: docker (>=4.1.0,<5.0.0)
Project-URL: Repository, https://github.com/TheEdgeOfRage/servicectl
